ICD10CodeLookUp/ICD10CodeLookUp.py
ICD10CodeLookUp/__init__.py
ICD10CodeLookUp-0.0.2.dist-info/LICENSE
ICD10CodeLookUp-0.0.2.dist-info/METADATA
ICD10CodeLookUp-0.0.2.dist-info/WHEEL
ICD10CodeLookUp-0.0.2.dist-info/top_level.txt
ICD10CodeLookUp-0.0.2.dist-info/RECORD
