Metadata-Version: 2.1
Name: ICD10CodeLookUp
Version: 0.0.2
Summary: ICD10CodeLookUp is a Python library that can be used to look up ICD10 Diagnosis Codes.
Home-page: https://github.com/famutimine/ICD10CodeLookUp
Author: Daniel Famutimi MD, MPH
Author-email: danielfamutimi@gmail.com
License: MIT
Keywords: ICD1O Code
Platform: UNKNOWN
Classifier: Development Status :: 5 - Production/Stable
Classifier: Intended Audience :: Developers
Classifier: Intended Audience :: Healthcare Industry
Classifier: Intended Audience :: System Administrators
Classifier: License :: OSI Approved :: MIT License
Classifier: Programming Language :: Python :: 3
Classifier: Programming Language :: Python :: 3.6
Classifier: Programming Language :: Python :: 3.7
Classifier: Programming Language :: Python :: 3.8
Classifier: Programming Language :: Python :: 3.9
Classifier: Topic :: Software Development :: Libraries :: Python Modules
Classifier: Topic :: Scientific/Engineering :: Information Analysis
Classifier: Intended Audience :: Healthcare Industry
License-File: LICENSE
Requires-Dist: numpy
Requires-Dist: pandas
